{
    "layers": [
        null,
        [
            {
                "bias": 0.7824251306983026,
                "wji": []
            },
            {
                "bias": -0.08191808906720222,
                "wji": []
            }
        ],
        [
            {
                "bias": 3.5799459927010013,
                "wji": [
                    -3.530134201660835,
                    -2.3616646574639906
                ]
            },
            {
                "bias": 2.5009226716838797,
                "wji": [
                    -1.5742685612465817,
                    -3.252489252364664
                ]
            },
            {
                "bias": 5.434305219029452,
                "wji": [
                    -4.0994955057182665,
                    -3.9625761763562455
                ]
            }
        ],
        [
            {
                "bias": -6.807744827141326,
                "wji": [
                    5.788329858736721,
                    4.469093566143388,
                    8.389017104426088
                ]
            }
        ]
    ],
    "settings": [
        2,
        3,
        1
    ]
}